dummytestlib/__init__.py
dummytestlib/myfunctions.py
dummytestlib-0.1.0.dist-info/METADATA
dummytestlib-0.1.0.dist-info/WHEEL
dummytestlib-0.1.0.dist-info/top_level.txt
dummytestlib-0.1.0.dist-info/RECORD
