Metadata-Version: 2.1
Name: dummytestlib
Version: 0.1.0
Summary: Dummy test library - no use yet.
Author: ME
